pik_wrapper
