Metadata-Version: 1.0
Name: python-pik-api-wrapper
Version: 1.3.7
Summary: Wrapper for the PIK Group website API
Home-page: https://github.com/drillcoder/python_pik_api_wrapper
Author: DrillCoder
Author-email: nitrodrill@ya.ru
License: UNKNOWN
Keywords: pik,wrapper,python
Platform: UNKNOWN
